.editorconfig
.gitignore
.gitlab-ci.yml
LICENSE
README.rst
publish.settings.sh
publish.sh
pyproject.toml
.idea/modules.xml
.idea/peek-storage-service.iml
.idea/inspectionProfiles/Project_Default.xml
.idea/inspectionProfiles/profiles_settings.xml
examples/test_mssql_connection.py
peek_storage_service/PlatformDependencyTest.py
peek_storage_service/__init__.py
peek_storage_service/run_peek_storage_service.py
peek_storage_service/winsvc_peek_storage_service.py
peek_storage_service.egg-info/PKG-INFO
peek_storage_service.egg-info/SOURCES.txt
peek_storage_service.egg-info/dependency_links.txt
peek_storage_service.egg-info/entry_points.txt
peek_storage_service.egg-info/requires.txt
peek_storage_service.egg-info/top_level.txt
peek_storage_service/_private/StorageInit.py
peek_storage_service/_private/__init__.py
peek_storage_service/_private/alembic.ini
peek_storage_service/_private/alembic/env.py
peek_storage_service/_private/alembic/script.py.mako
peek_storage_service/_private/alembic/objects/__init__.py
peek_storage_service/_private/alembic/objects/object_load_paylaod_tuples.py
peek_storage_service/_private/alembic/objects/object_run_generic_python.py
peek_storage_service/_private/alembic/versions/12a0ab3826f3_add_run_generic_python.py
peek_storage_service/_private/alembic/versions/2efc91c0f0f6_add_plpython3u.py
peek_storage_service/_private/alembic/versions/34490abd765c_add_pg_load_payload_tuples.py
peek_storage_service/_private/alembic/versions/51e48a6594d5_up1_run_generic_py.py
peek_storage_service/_private/alembic/versions/72518909970f_add_run_worker_plpy.py
peek_storage_service/_private/alembic/versions/__init__.py
peek_storage_service/_private/alembic/versions/bab14faf0cd7_add_timescale.py
peek_storage_service/_private/plugin/PeekStoragePlatformHook.py
peek_storage_service/_private/plugin/StoragePluginLoader.py
peek_storage_service/_private/plugin/StoragePluginLoaderTest.py
peek_storage_service/_private/plugin/__init__.py
peek_storage_service/_private/service/PeekStorageConfig.py
peek_storage_service/_private/service/StorageSiteResource.py
peek_storage_service/_private/service/__init__.py
peek_storage_service/_private/service/sw_download/PeekSwDownloadResource.py
