Metadata-Version: 2.4
Name: peek-storage-service
Version: 5.0.4
Summary: Peek Storage Service - where stroage of Peek is
Author-email: Synerty <contact@synerty.com>
Project-URL: Homepage, https://github.com/Synerty/peek-storage-service
Keywords: Peek,Python,Platform,synerty
License-File: LICENSE
Requires-Dist: peek-plugin-base==5.0.4
Requires-Dist: peek-platform==5.0.4
Dynamic: license-file
